Workbook

Sheet final_data
A1: Company_Name | B1: Class | C1: Designation | D1: Location | E1: Total_applicants | F1: Trustable Applicants | G1: LinkedIn_Followers | H1: Contract | I1: Level | J1: Employee_count | K1: Industry | L1: PYTHON | M1: C++ | N1: JAVA | O1: HADOOP | P1: SCALA | Q1: FLASK | R1: PANDAS | S1: SPARK | T1: NUMPY | U1: PHP | V1: SQL | W1: MYSQL | X1: CSS | Y1: MONGODB | Z1: NLTK | AA1: TENSORFLOW | AB1: LINUX | AC1: RUBY | AD1: JAVASCRIPT | AE1: DJANGO | AF1: REACT | AG1: REACTJS | AH1: AI | AI1: UI | AJ1: TABLEAU | AK1: NODEJS | AL1: EXCEL | AM1: POWER BI | AN1: SELENIUM | AO1: HTML | AP1: ML
A2: Wipro | B2: Class 3 | C2: Project Manager | D2: Maharashtra | E2: 0 | F2: =IF(final_data[[#This Row],[Total_applicants]]=0,"unknown","-") -> unknown | G2: 6737300 | H2: Full-time | I2: Entry level | J2: 10001 | K2: IT Services and IT Consulting | L2: 0 | M2: 0 | N2: 0 | O2: 0 | P2: 1 | Q2: 0 | R2: 0 | S2: 0 | T2: 0 | U2: 0 | V2: 0 | W2: 0 | X2: 0 | Y2: 0 | Z2: 0 | AA2: 0 | AB2: 0 | AC2: 0 | AD2: 0 | AE2: 0 | AF2: 0 | AG2: 0 | AH2: 1 | AI2: 1 | AJ2: 0 | AK2: 0 | AL2: 1 | AM2: 0 | AN2: 0 | AO2: 0 | AP2: 1
A3: Wipro | B3: Class 3 | C3: Project Manager | D3: Delhi | E3: 121 | F3: =IF(final_data[[#This Row],[Total_applicants]]=0,"unknown","-") -> - | G3: 6737300 | H3: Full-time | I3: Entry level | J3: 10001 | K3: IT Services and IT Consulting | L3: 0 | M3: 0 | N3: 0 | O3: 0 | P3: 1 | Q3: 0 | R3: 0 | S3: 0 | T3: 0 | U3: 0 | V3: 0 | W3: 0 | X3: 0 | Y3: 0 | Z3: 0 | AA3: 0 | AB3: 0 | AC3: 0 | AD3: 0 | AE3: 0 | AF3: 0 | AG3: 0 | AH3: 1 | AI3: 1 | AJ3: 0 | AK3: 0 | AL3: 1 | AM3: 0 | AN3: 0 | AO3: 0 | AP3: 1
A4: Wipro | B4: Class 3 | C4: Project Manager | D4: Delhi | E4: 0 | F4: =IF(final_data[[#This Row],[Total_applicants]]=0,"unknown","-") -> unknown | G4: 6737300 | H4: Full-time | I4: Entry level | J4: 10001 | K4: IT Services and IT Consulting | L4: 0 | M4: 0 | N4: 0 | O4: 0 | P4: 1 | Q4: 0 | R4: 0 | S4: 0 | T4: 0 | U4: 0 | V4: 0 | W4: 0 | X4: 0 | Y4: 0 | Z4: 0 | AA4: 0 | AB4: 0 | AC4: 0 | AD4: 0 | AE4: 0 | AF4: 0 | AG4: 0 | AH4: 1 | AI4: 1 | AJ4: 0 | AK4: 0 | AL4: 1 | AM4: 0 | AN4: 0 | AO4: 0 | AP4: 1
A5: Wipro | B5: Class 3 | C5: Administrator | D5: Telangana | E5: 0 | F5: =IF(final_data[[#This Row],[Total_applicants]]=0,"unknown","-") -> unknown | G5: 6737300 | H5: Full-time | I5: Mid-Senior level | J5: 10001 | K5: IT Services and IT Consulting | L5: 0 | M5: 0 | N5: 0 | O5: 0 | P5: 1 | Q5: 0 | R5: 0 | S5: 0 | T5: 0 | U5: 0 | V5: 0 | W5: 0 | X5: 0 | Y5: 0 | Z5: 0 | AA5: 0 | AB5: 0 | AC5: 0 | AD5: 0 | AE5: 0 | AF5: 0 | AG5: 0 | AH5: 1 | AI5: 1 | AJ5: 0 | AK5: 0 | AL5: 1 | AM5: 0 | AN5: 0 | AO5: 0 | AP5: 0
A6: Wipro | B6: Class 3 | C6: Project Manager | D6: Maharashtra | E6: 119 | F6: =IF(final_data[[#This Row],[Total_applicants]]=0,"unknown","-") -> - | G6: 6737300 | H6: Full-time | I6: Entry level | J6: 10001 | K6: IT Services and IT Consulting | L6: 0 | M6: 0 | N6: 0 | O6: 0 | P6: 1 | Q6: 0 | R6: 0 | S6: 0 | T6: 0 | U6: 0 | V6: 0 | W6: 0 | X6: 0 | Y6: 0 | Z6: 0 | AA6: 0 | AB6: 0 | AC6: 0 | AD6: 0 | AE6: 0 | AF6: 0 | AG6: 0 | AH6: 1 | AI6: 1 | AJ6: 0 | AK6: 0 | AL6: 1 | AM6: 0 | AN6: 0 | AO6: 0 | AP6: 1
A7: Wipro | B7: Class 3 | C7: Administrator | D7: Telangana | E7: 39 | F7: =IF(final_data[[#This Row],[Total_applicants]]=0,"unknown","-") -> - | G7: 6737300 | H7: Full-time | I7: Mid-Senior level | J7: 10001 | K7: IT Services and IT Consulting | L7: 0 | M7: 0 | N7: 0 | O7: 0 | P7: 1 | Q7: 0 | R7: 0 | S7: 0 | T7: 0 | U7: 0 | V7: 0 | W7: 0 | X7: 0 | Y7: 0 | Z7: 0 | AA7: 0 | AB7: 0 | AC7: 0 | AD7: 0 | AE7: 0 | AF7: 0 | AG7: 0 | AH7: 1 | AI7: 1 | AJ7: 0 | AK7: 0 | AL7: 1 | AM7: 0 | AN7: 0 | AO7: 0 | AP7: 0
A8: Wipro | B8: Class 3 | C8: Administrator | D8: Telangana | E8: 22 | F8: =IF(final_data[[#This Row],[Total_applicants]]=0,"unknown","-") -> - | G8: 6737300 | H8: Full-time | I8: Mid-Senior level | J8: 10001 | K8: IT Services and IT Consulting | L8: 0 | M8: 0 | N8: 0 | O8: 0 | P8: 1 | Q8: 0 | R8: 0 | S8: 0 | T8: 0 | U8: 0 | V8: 0 | W8: 0 | X8: 0 | Y8: 0 | Z8: 0 | AA8: 0 | AB8: 0 | AC8: 0 | AD8: 0 | AE8: 0 | AF8: 0 | AG8: 0 | AH8: 1 | AI8: 1 | AJ8: 0 | AK8: 0 | AL8: 1 | AM8: 0 | AN8: 0 | AO8: 0 | AP8: 0
A9: Wipro | B9: Class 3 | C9: Test Engineer | D9: Maharashtra | E9: 158 | F9: =IF(final_data[[#This Row],[Total_applicants]]=0,"unknown","-") -> - | G9: 6737300 | H9: Full-time | I9: Entry level | J9: 10001 | K9: IT Services and IT Consulting | L9: 0 | M9: 0 | N9: 0 | O9: 0 | P9: 0 | Q9: 0 | R9: 0 | S9: 0 | T9: 0 | U9: 0 | V9: 0 | W9: 0 | X9: 0 | Y9: 0 | Z9: 0 | AA9: 0 | AB9: 0 | AC9: 0 | AD9: 0 | AE9: 0 | AF9: 0 | AG9: 0 | AH9: 1 | AI9: 1 | AJ9: 0 | AK9: 0 | AL9: 1 | AM9: 0 | AN9: 0 | AO9: 0 | AP9: 0
A10: Wipro | B10: Class 3 | C10: Administrator | D10: Maharashtra | E10: 11 | F10: =IF(final_data[[#This Row],[Total_applicants]]=0,"unknown","-") -> - | G10: 6737300 | H10: Full-time | I10: Mid-Senior level | J10: 10001 | K10: IT Services and IT Consulting | L10: 0 | M10: 0 | N10: 0 | O10: 0 | P10: 1 | Q10: 0 | R10: 0 | S10: 0 | T10: 0 | U10: 0 | V10: 0 | W10: 0 | X10: 0 | Y10: 0 | Z10: 0 | AA10: 0 | AB10: 0 | AC10: 0 | AD10: 0 | AE10: 0 | AF10: 0 | AG10: 0 | AH10: 1 | AI10: 1 | AJ10: 0 | AK10: 0 | AL10: 1 | AM10: 0 | AN10: 0 | AO10: 0 | AP10: 0
A11: Wipro | B11: Class 3 | C11: Administrator | D11: Maharashtra | E11: 47 | F11: =IF(final_data[[#This Row],[Total_applicants]]=0,"unknown","-") -> - | G11: 6737300 | H11: Full-time | I11: Mid-Senior level | J11: 10001 | K11: IT Services and IT Consulting | L11: 0 | M11: 0 | N11: 0 | O11: 0 | P11: 1 | Q11: 0 | R11: 0 | S11: 0 | T11: 0 | U11: 0 | V11: 0 | W11: 0 | X11: 0 | Y11: 0 | Z11: 0 | AA11: 0 | AB11: 0 | AC11: 0 | AD11: 0 | AE11: 0 | AF11: 0 | AG11: 0 | AH11: 1 | AI11: 1 | AJ11: 0 | AK11: 0 | AL11: 1 | AM11: 0 | AN11: 0 | AO11: 0 | AP11: 0
A12: Wipro | B12: Class 3 | C12: Service Level Manager | D12: Maharashtra | E12: 20 | F12: =IF(final_data[[#This Row],[Total_applicants]]=0,"unknown","-") -> - | G12: 6737300 | H12: Full-time | I12: Mid-Senior level | J12: 10001 | K12: IT Services and IT Consulting | L12: 0 | M12: 0 | N12: 0 | O12: 0 | P12: 0 | Q12: 0 | R12: 0 | S12: 0 | T12: 0 | U12: 0 | V12: 0 | W12: 0 | X12: 0 | Y12: 0 | Z12: 0 | AA12: 0 | AB12: 0 | AC12: 0 | AD12: 0 | AE12: 0 | AF12: 0 | AG12: 0 | AH12: 1 | AI12: 1 | AJ12: 0 | AK12: 0 | AL12: 1 | AM12: 0 | AN12: 0 | AO12: 0 | AP12: 0
A13: Wipro | B13: Class 3 | C13: Administrator | D13: Maharashtra | E13: 71 | F13: =IF(final_data[[#This Row],[Total_applicants]]=0,"unknown","-") -> - | G13: 6737300 | H13: Full-time | I13: Mid-Senior level | J13: 10001 | K13: IT Services and IT Consulting | L13: 0 | M13: 0 | N13: 0 | O13: 0 | P13: 1 | Q13: 0 | R13: 0 | S13: 0 | T13: 0 | U13: 0 | V13: 0 | W13: 0 | X13: 0 | Y13: 0 | Z13: 0 | AA13: 0 | AB13: 0 | AC13: 0 | AD13: 0 | AE13: 0 | AF13: 0 | AG13: 0 | AH13: 1 | AI13: 1 | AJ13: 0 | AK13: 0 | AL13: 1 | AM13: 0 | AN13: 0 | AO13: 0 | AP13: 0
... A812: Genpact | B812: Class 1 | C812: Hiring for RTR- Jaipur | D812: Rajasthan | E812: 133 | F812: =IF(final_data[[#This Row],[Total_applicants]]=0,"unknown","-") -> - | G812: 2519518 | H812: Full-time | I812: Associate | J812: 10001 | K812: IT Services and IT Consulting | L812: 0 | M812: 0 | N812: 0 | O812: 0 | P812: 0 | Q812: 0 | R812: 0 | S812: 0 | T812: 0 | U812: 0 | V812: 0 | W812: 0 | X812: 0 | Y812: 0 | Z812: 0 | AA812: 0 | AB812: 0 | AC812: 0 | AD812: 0 | AE812: 0 | AF812: 0 | AG812: 0 | AH812: 1 | AI812: 1 | AJ812: 0 | AK812: 0 | AL812: 1 | AM812: 0 | AN812: 0 | AO812: 0 | AP812: 0

Sheet Planilha1
G4: Empresas | I4: Qtd. Vagas | J4: Qtd. Vagas sem Aplicações | K4: Vagas sem aplicações (%)
G5: Wipro | I5: =COUNTIF(final_data!A:A,Planilha1!G5) -> 102 | J5: =COUNTIFS(final_data!A:A,Planilha1!G5,final_data!E:E,0) -> 25 | K5: =J5/I5 -> 0.24509804
G6: LTIMindtree | I6: =COUNTIF(final_data!A:A,Planilha1!G6) -> 187 | J6: =COUNTIFS(final_data!A:A,Planilha1!G6,final_data!E:E,0) -> 34 | K6: =J6/I6 -> 0.18181818
G7: IDESLABS PRIVATE LIMITED | I7: =COUNTIF(final_data!A:A,Planilha1!G7) -> 265 | J7: =COUNTIFS(final_data!A:A,Planilha1!G7,final_data!E:E,0) -> 44 | K7: =J7/I7 -> 0.16603774
G8: Cactus Communications | I8: =COUNTIF(final_data!A:A,Planilha1!G8) -> 2 | J8: =COUNTIFS(final_data!A:A,Planilha1!G8,final_data!E:E,0) -> 0 | K8: =J8/I8 -> 0
G9: ACURA SOLUTIONS LTD | I9: =COUNTIF(final_data!A:A,Planilha1!G9) -> 97 | J9: =COUNTIFS(final_data!A:A,Planilha1!G9,final_data!E:E,0) -> 22 | K9: =J9/I9 -> 0.22680412
G10: UST | I10: =COUNTIF(final_data!A:A,Planilha1!G10) -> 1 | J10: =COUNTIFS(final_data!A:A,Planilha1!G10,final_data!E:E,0) -> 0 | K10: =J10/I10 -> 0
G11: Vodafone Idea Limited | I11: =COUNTIF(final_data!A:A,Planilha1!G11) -> 3 | J11: =COUNTIFS(final_data!A:A,Planilha1!G11,final_data!E:E,0) -> 0 | K11: =J11/I11 -> 0
G12: Tata Consultancy Services | I12: =COUNTIF(final_data!A:A,Planilha1!G12) -> 14 | J12: =COUNTIFS(final_data!A:A,Planilha1!G12,final_data!E:E,0) -> 1 | K12: =J12/I12 -> 0.071428571
G13: Uplers | I13: =COUNTIF(final_data!A:A,Planilha1!G13) -> 122 | J13: =COUNTIFS(final_data!A:A,Planilha1!G13,final_data!E:E,0) -> 0 | K13: =J13/I13 -> 0
G14: Infosys | I14: =COUNTIF(final_data!A:A,Planilha1!G14) -> 15 | J14: =COUNTIFS(final_data!A:A,Planilha1!G14,final_data!E:E,0) -> 0 | K14: =J14/I14 -> 0
G15: Genpact | I15: =COUNTIF(final_data!A:A,Planilha1!G15) -> 3 | J15: =COUNTIFS(final_data!A:A,Planilha1!G15,final_data!E:E,0) -> 0 | K15: =J15/I15 -> 0
E19: "Total_Applicants não confiáveis
E20: 126
